PDM.cpython-37m-darwin.so
autoeap/__init__.py
autoeap/aperture_to_fits.py
autoeap/autoeapcore.py
autoeap/detrender.py
autoeap/k2sc_stable.py
autoeap/photutils_stable.py
autoeap/version.py
autoeap-0.3.1.4.dist-info/LICENCE
autoeap-0.3.1.4.dist-info/METADATA
autoeap-0.3.1.4.dist-info/WHEEL
autoeap-0.3.1.4.dist-info/entry_points.txt
autoeap-0.3.1.4.dist-info/top_level.txt
autoeap-0.3.1.4.dist-info/RECORD
