Metadata-Version: 2.1
Name: autoeap
Version: 0.3.1.4
Summary: Automated version of Extended Aperture Photometry developed for high amplitude K2 variable stars.
Home-page: https://github.com/konkolyseismolab/autoeap/
Author: Attila Bodi & Pal Szabo
Author-email: bodi.attila@csfk.org
License: UNKNOWN
Platform: UNKNOWN
Requires-Dist: numpy (>=1.11)
Requires-Dist: scipy (!=1.4.0,!=1.4.1,>=0.19.0)
Requires-Dist: matplotlib (>=1.5.3)
Requires-Dist: lightkurve (<2.0.0,>=1.5)
Requires-Dist: scikit-learn
Requires-Dist: astropy (>=4.1rc1)
Requires-Dist: wotan
Requires-Dist: tqdm (>=4.25.0)
Requires-Dist: numba
Requires-Dist: memoization
Requires-Dist: oktopus
Requires-Dist: astroquery (!=0.4.2.dev0)
Requires-Dist: cython
